{"leads": {"95047a08f7924c279dd7c6261b355903": {"id": "95047a08f7924c279dd7c6261b355903", "brand_id": "brand1", "source": "webform", "name": "A", "email": "a@test.com", "phone": "919999988888", "company": "Mountt", "message": "call me", "utm": {"utm_source": "google", "utm_campaign": "c1"}, "raw": {"brand_id": "brand1", "company": "Mountt", "name": "A", "source": "webform", "phone": "+91 99999 88888", "message": "call me", "utm": {"utm_source": "google", "utm_campaign": "c1"}, "email": "a@test.com"}, "status": "pushed", "created_at": "2026-03-27T11:40:14.206783+00:00", "updated_at": "2026-03-27T11:40:14.273418+00:00", "dedupe_key": "brand1|email|a@test.com"}, "1632205dc5e54894853160b1cb62af39": {"id": "1632205dc5e54894853160b1cb62af39", "brand_id": "b1", "source": "web", "name": "X", "email": "a@b.com", "phone": null, "company": null, "message": null, "utm": null, "raw": {"brand_id": "b1", "email": "a@b.com", "name": "X"}, "status": "captured", "created_at": "2026-03-29T02:20:36.636906+00:00", "updated_at": "2026-03-29T02:20:36.636906+00:00", "dedupe_key": "b1|email|a@b.com"}, "ae10cd6d6aa24def85cab69d398d9405": {"id": "ae10cd6d6aa24def85cab69d398d9405", "brand_id": "b2", "source": "webhook", "name": null, "email": "c@d.com", "phone": null, "company": null, "message": null, "utm": null, "raw": {"brand_id": "b2", "email": "c@d.com"}, "status": "captured", "created_at": "2026-03-29T02:20:36.642721+00:00", "updated_at": "2026-03-29T02:20:36.642721+00:00", "dedupe_key": "b2|email|c@d.com"}, "f4434b274a94491ba407a1d86e7c4cfb": {"id": "f4434b274a94491ba407a1d86e7c4cfb", "brand_id": "demo", "source": "demo_ui", "name": "Test Lead", "email": null, "phone": "9999999999", "company": null, "message": "Interested in SalesPal demo", "utm": null, "raw": {"demo_ui": true}, "status": "captured", "created_at": "2026-04-05T14:12:20.044162+00:00", "updated_at": "2026-04-05T14:12:20.044162+00:00", "dedupe_key": "demo|phone|9999999999"}, "b1d6f9c5c12544faa1fe474b0246b0a2": {"id": "b1d6f9c5c12544faa1fe474b0246b0a2", "brand_id": "b1", "source": "api", "name": null, "email": "m1@test.com", "phone": null, "company": null, "message": null, "utm": null, "raw": {"brand_id": "b1", "email": "m1@test.com", "source": "api"}, "status": "captured", "created_at": "2026-04-06T03:55:17.285378+00:00", "updated_at": "2026-04-06T03:55:17.285378+00:00", "dedupe_key": "b1|email|m1@test.com"}, "627303a88cf944ca92a514b39deb8201": {"id": "627303a88cf944ca92a514b39deb8201", "brand_id": "b1", "source": "form", "name": null, "email": "form@test.com", "phone": null, "company": null, "message": null, "utm": {"source": "fb"}, "raw": {"brand_id": "b1", "email": "form@test.com", "source": "form", "utm": {"source": "fb"}}, "status": "captured", "created_at": "2026-04-06T03:55:17.286995+00:00", "updated_at": "2026-04-06T03:55:17.286995+00:00", "dedupe_key": "b1|email|form@test.com"}}, "index": {"brand1|email|a@test.com": "95047a08f7924c279dd7c6261b355903", "b1|email|a@b.com": "1632205dc5e54894853160b1cb62af39", "b2|email|c@d.com": "ae10cd6d6aa24def85cab69d398d9405", "demo|phone|9999999999": "f4434b274a94491ba407a1d86e7c4cfb", "b1|email|m1@test.com": "b1d6f9c5c12544faa1fe474b0246b0a2", "b1|email|form@test.com": "627303a88cf944ca92a514b39deb8201"}, "idempotency": {"b1|k1": "1632205dc5e54894853160b1cb62af39"}}