{"f1968fed945948a69e60993724e48b69": {"id": "f1968fed945948a69e60993724e48b69", "brand_id": "brand1", "provider": "mock", "channel": "instagram", "asset_job_id": "129777a2ca8042c0b91d0c801c82dd3b", "caption": "hello", "scheduled_at": "2026-03-27T11:33:57.323313+00:00", "status": "posted", "attempt_count": 0, "max_attempts": 3, "next_attempt_at": "2026-03-27T11:33:57.323313+00:00", "created_at": "2026-03-27T11:33:57.323348+00:00", "updated_at": "2026-03-27T11:33:57.344780+00:00", "provider_post_id": "brand1-instagram-mock", "provider_response": {"provider": "mock", "channel": "instagram", "caption": "hello", "asset_keys": ["images_base64", "prompt"]}, "error": null}}